pixeltable/__init__.py
pixeltable/_query.py
pixeltable/_version.py
pixeltable/config.py
pixeltable/env.py
pixeltable/exceptions.py
pixeltable/globals.py
pixeltable/plan.py
pixeltable/py.typed
pixeltable/store.py
pixeltable/type_system.py
pixeltable/catalog/__init__.py
pixeltable/catalog/catalog.py
pixeltable/catalog/column.py
pixeltable/catalog/dir.py
pixeltable/catalog/globals.py
pixeltable/catalog/insertable_table.py
pixeltable/catalog/path.py
pixeltable/catalog/schema_object.py
pixeltable/catalog/table.py
pixeltable/catalog/table_metadata.py
pixeltable/catalog/table_version.py
pixeltable/catalog/table_version_handle.py
pixeltable/catalog/table_version_path.py
pixeltable/catalog/tbl_ops.py
pixeltable/catalog/update_status.py
pixeltable/catalog/view.py
pixeltable/exec/__init__.py
pixeltable/exec/aggregation_node.py
pixeltable/exec/cache_prefetch_node.py
pixeltable/exec/cell_materialization_node.py
pixeltable/exec/cell_reconstruction_node.py
pixeltable/exec/component_iteration_node.py
pixeltable/exec/data_row_batch.py
pixeltable/exec/exec_context.py
pixeltable/exec/exec_node.py
pixeltable/exec/globals.py
pixeltable/exec/in_memory_data_node.py
pixeltable/exec/object_store_save_node.py
pixeltable/exec/row_update_node.py
pixeltable/exec/sql_node.py
pixeltable/exec/expr_eval/__init__.py
pixeltable/exec/expr_eval/evaluators.py
pixeltable/exec/expr_eval/expr_eval_node.py
pixeltable/exec/expr_eval/globals.py
pixeltable/exec/expr_eval/row_buffer.py
pixeltable/exec/expr_eval/schedulers.py
pixeltable/exprs/__init__.py
pixeltable/exprs/arithmetic_expr.py
pixeltable/exprs/array_slice.py
pixeltable/exprs/column_property_ref.py
pixeltable/exprs/column_ref.py
pixeltable/exprs/comparison.py
pixeltable/exprs/compound_predicate.py
pixeltable/exprs/data_row.py
pixeltable/exprs/expr.py
pixeltable/exprs/expr_dict.py
pixeltable/exprs/expr_set.py
pixeltable/exprs/function_call.py
pixeltable/exprs/globals.py
pixeltable/exprs/in_predicate.py
pixeltable/exprs/inline_expr.py
pixeltable-0.5.10.dist-info/METADATA
pixeltable-0.5.10.dist-info/WHEEL
pixeltable-0.5.10.dist-info/entry_points.txt
pixeltable-0.5.10.dist-info/licenses/LICENSE
pixeltable-0.5.10.dist-info/RECORD
