Metadata-Version: 2.4
Name: pixeltable
Version: 0.5.10
Summary: AI Data Infrastructure: Declarative, Multimodal, and Incremental
Project-URL: homepage, https://pixeltable.com/
Project-URL: repository, https://github.com/pixeltable/pixeltable
Project-URL: documentation, https://docs.pixeltable.com/
Author-email: "Pixeltable, Inc." <contact@pixeltable.com>
License-Expression: Apache-2.0
License-File: LICENSE
Keywords: ai,artificial-intelligence,chatbot,computer-vision,data-science,database,feature-engineering,feature-store,genai,llm,machine-learning,ml,mlops,multimodal,vector-database
Classifier: Intended Audience :: Developers
Classifier: Intended Audience :: Science/Research
Classifier: License :: OSI Approved :: Apache Software License
Classifier: Operating System :: MacOS
Classifier: Operating System :: Microsoft :: Windows
Classifier: Operating System :: POSIX :: Linux
Classifier: Programming Language :: Python :: 3.10
Classifier: Programming Language :: Python :: 3.11
Classifier: Programming Language :: Python :: 3.12
Classifier: Programming Language :: Python :: 3.13
Classifier: Topic :: Database
Classifier: Topic :: Scientific/Engineering :: Artificial Intelligence
Classifier: Topic :: Software Development :: Libraries :: Python Modules
Requires-Python: >=3.10
Requires-Dist: aiohttp>=3.10
Requires-Dist: av>=10.0.0
Requires-Dist: beautifulsoup4>=4.10
Requires-Dist: cloudpickle>=2.2.1
Requires-Dist: deprecated>=1.2.15
Requires-Dist: ftfy>=6.2.0
Requires-Dist: httpcore>=1.0.3
Requires-Dist: httpx>=0.27
Requires-Dist: jinja2>=3.1.3
Requires-Dist: jmespath>=1.0.1
Requires-Dist: jsonschema>=4.1.0
Requires-Dist: lxml>=5.1
Requires-Dist: more-itertools>=10.2
Requires-Dist: nest-asyncio>=1.5
Requires-Dist: numpy>=1.25
Requires-Dist: pandas>=2.0
Requires-Dist: pgvector>=0.4.0
Requires-Dist: pillow-heif>=0.15.0
Requires-Dist: pillow>=9.3.0
Requires-Dist: pixeltable-pgserver==0.4.0
Requires-Dist: psycopg[binary]>=3.1.18
Requires-Dist: puremagic>=1.20
Requires-Dist: pyarrow>=19
Requires-Dist: pydantic>=2.7.4
Requires-Dist: pypdfium2>=4.30.0
Requires-Dist: pyyaml>=6.0.1
Requires-Dist: requests>=2.31.0
Requires-Dist: rich>=13.0
Requires-Dist: sqlalchemy>=2.0.23
Requires-Dist: tenacity>=8.2
Requires-Dist: toml>=0.10
Requires-Dist: tzlocal>=5.0
